Metadata-Version: 2.1
Name: sshdjup
Version: 0.4
Summary: UNKNOWN
Home-page: UNKNOWN
Author-email: yariksvitlitskiy81@gmail.com
License: UNKNOWN
Platform: UNKNOWN
